oneapi/__init__.py
oneapi/chat.py
oneapi/one_api.py
oneapi/one_api_test.py
oneapi/utils.py
oneapi/clients/__init__.py
oneapi/clients/abc_client.py
oneapi/clients/anthropic_client.py
oneapi/clients/claude_client.py
oneapi/clients/hf_client.py
oneapi/clients/openai_client.py
oneapi/clients/vllm_client.py
oneapi/commands/__init__.py
oneapi/commands/one_api_requst.py
one_api_tool-1.3.0.dist-info/LICENSE
one_api_tool-1.3.0.dist-info/METADATA
one_api_tool-1.3.0.dist-info/WHEEL
one_api_tool-1.3.0.dist-info/entry_points.txt
one_api_tool-1.3.0.dist-info/top_level.txt
one_api_tool-1.3.0.dist-info/RECORD
