Metadata-Version: 2.1
Name: one-api-tool
Version: 1.3.0
Summary: Use only one line of code to call multiple model APIs similar to ChatGPT. Currently supported: Azure OpenAI Resource endpoint API, OpenAI Official API, and Anthropic Claude series model API.
Home-page: https://github.com/muximus3/OneAPI
Classifier: Development Status :: 3 - Alpha
Classifier: License :: OSI Approved :: MIT License
Classifier: Programming Language :: Python :: 3
Classifier: Operating System :: OS Independent
License-File: LICENSE
Requires-Dist: pydantic
Requires-Dist: openai >=1.2.3
Requires-Dist: anthropic >=0.6.0
Requires-Dist: huggingface-hub
Requires-Dist: requests
Requires-Dist: httpx
Requires-Dist: rich
Requires-Dist: inquirer
Requires-Dist: Jinja2
Requires-Dist: aiohttp
Requires-Dist: tiktoken
Requires-Dist: python-dotenv
Requires-Dist: tqdm
Requires-Dist: tokenizers
Requires-Dist: docstring-parser
